sparql_llm/__init__.py
sparql_llm/config.py
sparql_llm/mcp_server.py
sparql_llm/py.typed
sparql_llm/utils.py
sparql_llm/validate_sparql.py
sparql_llm/agent/graph.py
sparql_llm/agent/main.py
sparql_llm/agent/prompts.py
sparql_llm/agent/state.py
sparql_llm/agent/utils.py
sparql_llm/agent/nodes/call_model.py
sparql_llm/agent/nodes/llm_extraction.py
sparql_llm/agent/nodes/mcp_tools.py
sparql_llm/agent/nodes/retrieval_docs.py
sparql_llm/agent/nodes/retrieval_entities.py
sparql_llm/agent/nodes/validation.py
sparql_llm/agent/webapp/index.html
sparql_llm/agent/webapp/assets/index-DUrw8Cxs.css
sparql_llm/agent/webapp/assets/index-Dp5RABF9.js
sparql_llm/agent/webapp/assets/sib-logo--jUM9mer.png
sparql_llm/indexing/index_entities.py
sparql_llm/indexing/index_resources.py
sparql_llm/loaders/sparql_examples_loader.py
sparql_llm/loaders/sparql_info_loader.py
sparql_llm/loaders/sparql_void_shapes_loader.py
sparql_llm-0.1.4.dist-info/METADATA
sparql_llm-0.1.4.dist-info/WHEEL
sparql_llm-0.1.4.dist-info/entry_points.txt
sparql_llm-0.1.4.dist-info/licenses/LICENSE.txt
sparql_llm-0.1.4.dist-info/RECORD
