Metadata-Version: 2.4
Name: sparql-llm
Version: 0.1.4
Summary: Reusable components and complete chat system to improve Large Language Models (LLMs) capabilities when generating SPARQL queries for a given set of endpoints, using Retrieval-Augmented Generation (RAG) and SPARQL query validation from the endpoint schema.
Project-URL: Homepage, https://github.com/sib-swiss/sparql-llm
Project-URL: Documentation, https://github.com/sib-swiss/sparql-llm
Project-URL: History, https://github.com/sib-swiss/sparql-llm/releases
Project-URL: Tracker, https://github.com/sib-swiss/sparql-llm/issues
Project-URL: Source, https://github.com/sib-swiss/sparql-llm
Author-email: Vincent Emonet <vincent.emonet@gmail.com>
Maintainer-email: Vincent Emonet <vincent.emonet@gmail.com>
License: MIT License
License-File: LICENSE.txt
Keywords: Chatbot,Expasy,KGQA,LLM,SPARQL
Classifier: License :: OSI Approved :: MIT License
Classifier: Operating System :: OS Independent
Classifier: Programming Language :: Python :: 3
Classifier: Programming Language :: Python :: 3.10
Classifier: Programming Language :: Python :: 3.11
Classifier: Programming Language :: Python :: 3.12
Classifier: Programming Language :: Python :: 3.13
Requires-Python: >=3.10
Requires-Dist: beautifulsoup4>=4.13.0
Requires-Dist: curies>=0.11.0
Requires-Dist: fastembed>=0.7.4
Requires-Dist: httpx>=0.27.2
Requires-Dist: langchain-core>=1.2.6
Requires-Dist: markdownify>=1.1.0
Requires-Dist: mcp<2,>=1.25.0
Requires-Dist: pandas>=2.2.3
Requires-Dist: qdrant-client>=1.16.2
Requires-Dist: rdflib>=7.0.0
Requires-Dist: sparqlwrapper>=2.0.0
Requires-Dist: typing-extensions>=4.15.0
Provides-Extra: agent
Requires-Dist: fastapi>=0.123.0; extra == 'agent'
Requires-Dist: jinja2>=3.1.5; extra == 'agent'
Requires-Dist: joblib>=1.5.2; extra == 'agent'
Requires-Dist: langchain-mcp-adapters>=0.2.1; extra == 'agent'
Requires-Dist: langchain-openai>=1.1.6; extra == 'agent'
Requires-Dist: langchain>=1.2.0; extra == 'agent'
Requires-Dist: langfuse>=3.8.1; extra == 'agent'
Requires-Dist: langgraph>=1.0.5; extra == 'agent'
Requires-Dist: matplotlib>=3.10.3; extra == 'agent'
Requires-Dist: pydantic-settings>=2.7.0; extra == 'agent'
Requires-Dist: pydantic>=2.10.0; extra == 'agent'
Requires-Dist: seaborn>=0.13.2; extra == 'agent'
Requires-Dist: sentry-sdk[fastapi]>=2.27.0; extra == 'agent'
Requires-Dist: uvicorn[standard]>=0.34.0; extra == 'agent'
